odoo/addons/product_standard_price_tax_included/README.rst
odoo/addons/product_standard_price_tax_included/__init__.py
odoo/addons/product_standard_price_tax_included/__manifest__.py
odoo/addons/product_standard_price_tax_included/demo/account_tax.xml
odoo/addons/product_standard_price_tax_included/demo/product_pricelist.xml
odoo/addons/product_standard_price_tax_included/demo/product_product.xml
odoo/addons/product_standard_price_tax_included/i18n/ca.po
odoo/addons/product_standard_price_tax_included/i18n/de.po
odoo/addons/product_standard_price_tax_included/i18n/es.po
odoo/addons/product_standard_price_tax_included/i18n/fr.po
odoo/addons/product_standard_price_tax_included/i18n/it.po
odoo/addons/product_standard_price_tax_included/i18n/product_standard_price_tax_included.pot
odoo/addons/product_standard_price_tax_included/i18n/sl.po
odoo/addons/product_standard_price_tax_included/models/__init__.py
odoo/addons/product_standard_price_tax_included/models/product_pricelist_item.py
odoo/addons/product_standard_price_tax_included/models/product_product.py
odoo/addons/product_standard_price_tax_included/models/product_template.py
odoo/addons/product_standard_price_tax_included/readme/CONFIGURE.rst
odoo/addons/product_standard_price_tax_included/readme/CONTRIBUTORS.rst
odoo/addons/product_standard_price_tax_included/readme/DESCRIPTION.rst
odoo/addons/product_standard_price_tax_included/static/description/icon.png
odoo/addons/product_standard_price_tax_included/static/description/index.html
odoo/addons/product_standard_price_tax_included/static/description/product_pricelist_item_form.png
odoo/addons/product_standard_price_tax_included/static/description/sale_order_form_with_module.png
odoo/addons/product_standard_price_tax_included/static/description/sale_order_form_without_module.png
odoo/addons/product_standard_price_tax_included/tests/__init__.py
odoo/addons/product_standard_price_tax_included/tests/test_module.py
odoo_addon_product_standard_price_tax_included-16.0.1.0.1.5.dist-info/METADATA
odoo_addon_product_standard_price_tax_included-16.0.1.0.1.5.dist-info/WHEEL
odoo_addon_product_standard_price_tax_included-16.0.1.0.1.5.dist-info/top_level.txt
odoo_addon_product_standard_price_tax_included-16.0.1.0.1.5.dist-info/RECORD
