Metadata-Version: 2.1
Name: odoo-addon-product-standard-price-tax-included
Version: 16.0.1.0.1.5
Summary: Brings a Cost Price Field Tax Included on Product Model
Home-page: https://github.com/OCA/product-attribute
Author: GRAP,Odoo Community Association (OCA)
Author-email: support@odoo-community.org
License: AGPL-3
Platform: UNKNOWN
Classifier: Programming Language :: Python
Classifier: Framework :: Odoo
Classifier: Framework :: Odoo :: 16.0
Classifier: License :: OSI Approved :: GNU Affero General Public License v3
Classifier: Development Status :: 4 - Beta
Requires-Python: >=3.10
Requires-Dist: odoo <16.1dev,>=16.0a
